hicstuff/__init__.py
hicstuff/commands.py
hicstuff/cutsite.py
hicstuff/digest.py
hicstuff/distance_law.py
hicstuff/filter.py
hicstuff/hicstuff.py
hicstuff/io.py
hicstuff/iteralign.py
hicstuff/log.py
hicstuff/main.py
hicstuff/pipeline.py
hicstuff/stats.py
hicstuff/version.py
hicstuff/view.py
tests/__init__.py
tests/test_commands.py
tests/test_digest.py
tests/test_distance_law.py
tests/test_doctests.py
tests/test_filter.py
tests/test_hicstuff.py
tests/test_io.py
tests/test_pipeline.py
hicstuff-3.2.4.dist-info/LICENSE
hicstuff-3.2.4.dist-info/METADATA
hicstuff-3.2.4.dist-info/WHEEL
hicstuff-3.2.4.dist-info/entry_points.txt
hicstuff-3.2.4.dist-info/top_level.txt
hicstuff-3.2.4.dist-info/RECORD
