Metadata-Version: 2.1
Name: hicstuff
Version: 3.2.4
Summary: General purpose stuff to generate and handle Hi-C data in its simplest form.
Home-page: https://github.com/koszullab/hicstuff
Author: cyril.matthey-doret@pasteur.fr
License: BSD-3-Clause
Platform: UNKNOWN
Classifier: Development Status :: 5 - Production/Stable
Classifier: Intended Audience :: Science/Research
Classifier: Intended Audience :: Science/Research
Classifier: License :: OSI Approved :: BSD License
Classifier: Programming Language :: Python
Classifier: Programming Language :: Python :: 3
Classifier: Programming Language :: Python :: 3 :: Only
Classifier: Programming Language :: Python :: 3.7
Classifier: Programming Language :: Python :: 3.8
Classifier: Programming Language :: Python :: 3.9
Classifier: Topic :: Scientific/Engineering
Classifier: Topic :: Scientific/Engineering :: Bio-Informatics
Classifier: Topic :: Scientific/Engineering :: Visualization
Classifier: Operating System :: POSIX
Classifier: Operating System :: Unix
Classifier: Operating System :: MacOS
Requires-Python: >=3.6
Requires-Dist: numpy
Requires-Dist: scipy
Requires-Dist: pandas>=1.5.0
Requires-Dist: matplotlib>=3.4.0
Requires-Dist: docopt
Requires-Dist: biopython
Requires-Dist: requests
Requires-Dist: scikit-learn
Requires-Dist: pysam
Requires-Dist: pyfastx
Requires-Dist: cooler
Requires-Dist: pairtools
Provides-Extra: mappy
Requires-Dist: mappy; extra == "mappy"
